{
  "last_updated": "2026-03-13T11:29:32Z",
  "trends": {
    "stocks": "Bad",
    "budgets": "Same",
    "workforce": "Same"
  },
  "stock_weekly": [
    {
      "ticker": "BAH",
      "name": "Booz Allen Hamilton",
      "sector": "Consulting/Defense",
      "pct_change": -3.370930248789001
    },
    {
      "ticker": "SPY",
      "name": "SPDR S&P 500",
      "sector": "Index",
      "pct_change": -2.2383349803535615
    },
    {
      "ticker": "SAIC",
      "name": "SAIC",
      "sector": "Defense/IT",
      "pct_change": -2.0019298504112735
    },
    {
      "ticker": "^IXIC",
      "name": "NASDAQ",
      "sector": "Index",
      "pct_change": -1.9210073111933283
    },
    {
      "ticker": "GD",
      "name": "General Dynamics",
      "sector": "Defense",
      "pct_change": -1.5164959899040713
    },
    {
      "ticker": "LDOS",
      "name": "Leidos",
      "sector": "Defense/Cyber",
      "pct_change": -1.053174350988972
    },
    {
      "ticker": "NOC",
      "name": "Northrop Grumman",
      "sector": "Defense",
      "pct_change": -0.5013475390463007
    },
    {
      "ticker": "RTX",
      "name": "RTX",
      "sector": "Defense",
      "pct_change": -0.4022404207611446
    },
    {
      "ticker": "LMT",
      "name": "Lockheed Martin",
      "sector": "Defense",
      "pct_change": -0.33129510078721375
    }
  ]
}